{
  "snapshot": {
    "project": {
      "name": "M2.0 Diff Fixture",
      "currency": "SAR",
      "modelType": "monthly",
      "startDate": "2026-01-01",
      "status": "draft",
      "location": "Riyadh"
    },
    "phases": [
      {
        "id": "phase_1",
        "name": "Phase 1",
        "constructionStart": 1,
        "constructionPeriods": 24,
        "operationsPeriods": 60,
        "overlapPeriods": 0
      },
      {
        "id": "phase_2",
        "name": "Phase 2",
        "constructionStart": 25,
        "constructionPeriods": 18,
        "operationsPeriods": 60,
        "overlapPeriods": 6
      }
    ],
    "parcels": [
      {
        "id": "parcel_1",
        "phaseId": "phase_1",
        "name": "Parcel A",
        "area": 80000,
        "rate": 600,
        "cashPct": 70,
        "inKindPct": 30
      },
      {
        "id": "parcel_2",
        "phaseId": "phase_1",
        "name": "Parcel B",
        "area": 40000,
        "rate": 400,
        "cashPct": 50,
        "inKindPct": 50
      }
    ],
    "landAllocationMode": "autoByBua",
    "assets": [
      {
        "id": "asset_1",
        "phaseId": "phase_1",
        "name": "Apartments",
        "type": "High-end Apartments",
        "strategy": "Sell",
        "visible": true,
        "gfaSqm": 0,
        "buaSqm": 0,
        "sellableBuaSqm": 0,
        "parkingBaysRequired": 200
      },
      {
        "id": "asset_2",
        "phaseId": "phase_1",
        "name": "Hotel",
        "type": "Hotel 5-star",
        "strategy": "Operate",
        "visible": true,
        "gfaSqm": 0,
        "buaSqm": 0,
        "sellableBuaSqm": 0,
        "parkingBaysRequired": 80
      },
      {
        "id": "asset_3",
        "phaseId": "phase_1",
        "name": "Retail",
        "type": "Retail",
        "strategy": "Lease",
        "visible": true,
        "gfaSqm": 0,
        "buaSqm": 0,
        "sellableBuaSqm": 0,
        "parkingBaysRequired": 60
      },
      {
        "id": "asset_4",
        "phaseId": "phase_1",
        "name": "Branded Residences",
        "type": "Branded Residences",
        "strategy": "Hybrid",
        "visible": true,
        "gfaSqm": 0,
        "buaSqm": 0,
        "sellableBuaSqm": 0,
        "parkingBaysRequired": 30
      }
    ],
    "subUnits": [
      {
        "id": "subunit_1",
        "assetId": "asset_1",
        "name": "2BR",
        "category": "Sellable",
        "metric": "count",
        "metricValue": 120,
        "unitArea": 110,
        "unitPrice": 1500000
      },
      {
        "id": "subunit_2",
        "assetId": "asset_2",
        "name": "Hotel Key",
        "category": "Operable",
        "metric": "count",
        "metricValue": 220,
        "unitArea": 45,
        "unitPrice": 850,
        "occupancyPct": 65,
        "operatingMargin": 35
      },
      {
        "id": "subunit_3",
        "assetId": "asset_3",
        "name": "GLA",
        "category": "Leasable",
        "metric": "area",
        "metricValue": 5500,
        "unitPrice": 1200,
        "occupancyPct": 92,
        "operatingMargin": 80
      },
      {
        "id": "subunit_4",
        "assetId": "asset_4",
        "name": "Penthouse",
        "category": "Sellable",
        "metric": "count",
        "metricValue": 20,
        "unitArea": 220,
        "unitPrice": 5000000
      }
    ],
    "costLines": [
      {
        "id": "land-cash",
        "phaseId": "phase_1",
        "name": "Land (Cash Portion)",
        "method": "percent_of_cash_land",
        "value": 100,
        "stage": "land",
        "scope": "direct",
        "allocationBasis": "land_share",
        "startPeriod": 0,
        "endPeriod": 0,
        "phasing": "even",
        "isLocked": true
      },
      {
        "id": "site-prep",
        "phaseId": "phase_1",
        "name": "Site Preparation",
        "method": "rate_per_land",
        "value": 15,
        "stage": "hard",
        "scope": "direct",
        "allocationBasis": "land_share",
        "startPeriod": 1,
        "endPeriod": 12,
        "phasing": "even"
      },
      {
        "id": "infrastructure",
        "phaseId": "phase_1",
        "name": "Infrastructure",
        "method": "rate_per_nda",
        "value": 80,
        "stage": "hard",
        "scope": "direct",
        "allocationBasis": "land_share",
        "startPeriod": 1,
        "endPeriod": 13,
        "phasing": "even"
      },
      {
        "id": "structural",
        "phaseId": "phase_1",
        "name": "Structural Works",
        "method": "rate_per_gfa",
        "value": 400,
        "stage": "hard",
        "scope": "direct",
        "allocationBasis": "gfa_share",
        "startPeriod": 1,
        "endPeriod": 24,
        "phasing": "frontloaded"
      },
      {
        "id": "mep",
        "phaseId": "phase_1",
        "name": "MEP Works",
        "method": "rate_per_gfa",
        "value": 150,
        "stage": "hard",
        "scope": "direct",
        "allocationBasis": "gfa_share",
        "startPeriod": 11,
        "endPeriod": 24,
        "phasing": "even"
      },
      {
        "id": "finishing",
        "phaseId": "phase_1",
        "name": "Finishing Works",
        "method": "rate_per_bua",
        "value": 200,
        "stage": "hard",
        "scope": "direct",
        "allocationBasis": "bua_share",
        "startPeriod": 12,
        "endPeriod": 24,
        "phasing": "backloaded"
      },
      {
        "id": "professional-fees",
        "phaseId": "phase_1",
        "name": "Professional Fees",
        "method": "percent_of_construction",
        "value": 8,
        "stage": "soft",
        "scope": "indirect",
        "allocationBasis": "bua_share",
        "startPeriod": 1,
        "endPeriod": 24,
        "phasing": "even"
      },
      {
        "id": "contingency",
        "phaseId": "phase_1",
        "name": "Contingency",
        "method": "percent_of_construction",
        "value": 5,
        "stage": "soft",
        "scope": "indirect",
        "allocationBasis": "bua_share",
        "startPeriod": 1,
        "endPeriod": 24,
        "phasing": "even"
      },
      {
        "id": "marketing",
        "phaseId": "phase_1",
        "name": "Marketing & Sales",
        "method": "percent_of_total_land",
        "value": 2,
        "stage": "soft",
        "scope": "indirect",
        "allocationBasis": "bua_share",
        "startPeriod": 11,
        "endPeriod": 24,
        "phasing": "backloaded"
      },
      {
        "id": "project-management",
        "phaseId": "phase_1",
        "name": "Project Management",
        "method": "percent_of_construction",
        "value": 3,
        "stage": "soft",
        "scope": "indirect",
        "allocationBasis": "bua_share",
        "startPeriod": 1,
        "endPeriod": 24,
        "phasing": "even"
      },
      {
        "id": "legal",
        "phaseId": "phase_1",
        "name": "Legal & Admin",
        "method": "percent_of_total_land",
        "value": 1,
        "stage": "soft",
        "scope": "indirect",
        "allocationBasis": "bua_share",
        "startPeriod": 1,
        "endPeriod": 12,
        "phasing": "frontloaded"
      },
      {
        "id": "landscaping",
        "phaseId": "phase_1",
        "name": "Landscaping & External",
        "method": "rate_per_nda",
        "value": 30,
        "stage": "hard",
        "scope": "direct",
        "allocationBasis": "land_share",
        "startPeriod": 12,
        "endPeriod": 24,
        "phasing": "backloaded"
      },
      {
        "id": "ffe",
        "phaseId": "phase_1",
        "name": "FF&E / Interior Design",
        "method": "rate_per_bua",
        "value": 50,
        "stage": "hard",
        "scope": "direct",
        "allocationBasis": "bua_share",
        "startPeriod": 24,
        "endPeriod": 24,
        "phasing": "even"
      },
      {
        "id": "land-cash",
        "phaseId": "phase_2",
        "name": "Land (Cash Portion)",
        "method": "percent_of_cash_land",
        "value": 100,
        "stage": "land",
        "scope": "direct",
        "allocationBasis": "land_share",
        "startPeriod": 0,
        "endPeriod": 0,
        "phasing": "even",
        "isLocked": true
      },
      {
        "id": "site-prep",
        "phaseId": "phase_2",
        "name": "Site Preparation",
        "method": "rate_per_land",
        "value": 15,
        "stage": "hard",
        "scope": "direct",
        "allocationBasis": "land_share",
        "startPeriod": 1,
        "endPeriod": 12,
        "phasing": "even"
      },
      {
        "id": "infrastructure",
        "phaseId": "phase_2",
        "name": "Infrastructure",
        "method": "rate_per_nda",
        "value": 80,
        "stage": "hard",
        "scope": "direct",
        "allocationBasis": "land_share",
        "startPeriod": 1,
        "endPeriod": 13,
        "phasing": "even"
      },
      {
        "id": "structural",
        "phaseId": "phase_2",
        "name": "Structural Works",
        "method": "rate_per_gfa",
        "value": 400,
        "stage": "hard",
        "scope": "direct",
        "allocationBasis": "gfa_share",
        "startPeriod": 1,
        "endPeriod": 24,
        "phasing": "frontloaded"
      },
      {
        "id": "mep",
        "phaseId": "phase_2",
        "name": "MEP Works",
        "method": "rate_per_gfa",
        "value": 150,
        "stage": "hard",
        "scope": "direct",
        "allocationBasis": "gfa_share",
        "startPeriod": 11,
        "endPeriod": 24,
        "phasing": "even"
      },
      {
        "id": "finishing",
        "phaseId": "phase_2",
        "name": "Finishing Works",
        "method": "rate_per_bua",
        "value": 200,
        "stage": "hard",
        "scope": "direct",
        "allocationBasis": "bua_share",
        "startPeriod": 12,
        "endPeriod": 24,
        "phasing": "backloaded"
      },
      {
        "id": "professional-fees",
        "phaseId": "phase_2",
        "name": "Professional Fees",
        "method": "percent_of_construction",
        "value": 8,
        "stage": "soft",
        "scope": "indirect",
        "allocationBasis": "bua_share",
        "startPeriod": 1,
        "endPeriod": 24,
        "phasing": "even"
      },
      {
        "id": "contingency",
        "phaseId": "phase_2",
        "name": "Contingency",
        "method": "percent_of_construction",
        "value": 5,
        "stage": "soft",
        "scope": "indirect",
        "allocationBasis": "bua_share",
        "startPeriod": 1,
        "endPeriod": 24,
        "phasing": "even"
      },
      {
        "id": "marketing",
        "phaseId": "phase_2",
        "name": "Marketing & Sales",
        "method": "percent_of_total_land",
        "value": 2,
        "stage": "soft",
        "scope": "indirect",
        "allocationBasis": "bua_share",
        "startPeriod": 11,
        "endPeriod": 24,
        "phasing": "backloaded"
      },
      {
        "id": "project-management",
        "phaseId": "phase_2",
        "name": "Project Management",
        "method": "percent_of_construction",
        "value": 3,
        "stage": "soft",
        "scope": "indirect",
        "allocationBasis": "bua_share",
        "startPeriod": 1,
        "endPeriod": 24,
        "phasing": "even"
      },
      {
        "id": "legal",
        "phaseId": "phase_2",
        "name": "Legal & Admin",
        "method": "percent_of_total_land",
        "value": 1,
        "stage": "soft",
        "scope": "indirect",
        "allocationBasis": "bua_share",
        "startPeriod": 1,
        "endPeriod": 12,
        "phasing": "frontloaded"
      },
      {
        "id": "landscaping",
        "phaseId": "phase_2",
        "name": "Landscaping & External",
        "method": "rate_per_nda",
        "value": 30,
        "stage": "hard",
        "scope": "direct",
        "allocationBasis": "land_share",
        "startPeriod": 12,
        "endPeriod": 24,
        "phasing": "backloaded"
      },
      {
        "id": "ffe",
        "phaseId": "phase_2",
        "name": "FF&E / Interior Design",
        "method": "rate_per_bua",
        "value": 50,
        "stage": "hard",
        "scope": "direct",
        "allocationBasis": "bua_share",
        "startPeriod": 24,
        "endPeriod": 24,
        "phasing": "even"
      }
    ],
    "costOverrides": [],
    "financingTranches": [
      {
        "id": "tranche_1",
        "phaseId": "phase_1",
        "name": "Senior debt",
        "ltvPct": 60,
        "interestRatePct": 7.5,
        "drawdownMethod": "capex_basis",
        "repaymentMethod": "straight_line",
        "repaymentPeriods": 60,
        "idcCapitalize": true
      },
      {
        "id": "tranche_2",
        "phaseId": "phase_2",
        "name": "Senior debt",
        "ltvPct": 60,
        "interestRatePct": 7.5,
        "drawdownMethod": "capex_basis",
        "repaymentMethod": "straight_line",
        "repaymentPeriods": 60,
        "idcCapitalize": true
      }
    ],
    "equityContributions": []
  },
  "derived": {
    "land": {
      "totalAreaSqm": 120000,
      "totalValue": 64000000,
      "cashValue": 41600000,
      "inKindValue": 22400000,
      "weightedRate": 533.3333333333334
    },
    "projectEnd": "2034-01-01",
    "perAsset": [
      {
        "id": "asset_1",
        "bua": 13200,
        "sellable": 13200,
        "land": 25600000,
        "cost": {
          "byLineId": {
            "land-cash": 6656000,
            "site-prep": 288000,
            "infrastructure": 1536000,
            "structural": 0,
            "mep": 0,
            "finishing": 1056000,
            "marketing": 204800,
            "legal": 102400,
            "landscaping": 576000,
            "ffe": 264000,
            "professional-fees": 297600,
            "contingency": 186000,
            "project-management": 111600
          },
          "byStage": {
            "land": 6656000,
            "hard": 3720000,
            "soft": 902400,
            "operating": 0
          },
          "total": 11278400,
          "perPeriod": [
            6656000,
            182707.6923076923,
            181394.8717948718,
            180082.05128205128,
            178769.23076923078,
            177456.41025641025,
            176143.58974358975,
            174830.76923076922,
            173517.94871794872,
            172205.12820512822,
            170892.3076923077,
            171529.96336996337,
            190101.68498168496,
            184673.40659340663,
            86404.10256410256,
            106288.6446886447,
            126173.18681318681,
            146057.7289377289,
            165942.2710622711,
            185826.8131868132,
            205711.35531135532,
            225595.89743589744,
            245480.43956043955,
            265364.98168498167,
            549249.5238095238
          ]
        }
      },
      {
        "id": "asset_2",
        "bua": 9900,
        "sellable": 9900,
        "land": 19200000,
        "cost": {
          "byLineId": {
            "land-cash": 3744000,
            "site-prep": 162000,
            "infrastructure": 864000,
            "structural": 0,
            "mep": 0,
            "finishing": 594000,
            "marketing": 115200,
            "legal": 57600,
            "landscaping": 324000,
            "ffe": 148500,
            "professional-fees": 167400,
            "contingency": 104625,
            "project-management": 62775
          },
          "byStage": {
            "land": 3744000,
            "hard": 2092500,
            "soft": 507600,
            "operating": 0
          },
          "total": 6344100,
          "perPeriod": [
            3744000,
            102773.07692307694,
            102034.61538461539,
            101296.15384615386,
            100557.69230769231,
            99819.23076923078,
            99080.76923076923,
            98342.3076923077,
            97603.84615384616,
            96865.38461538462,
            96126.92307692308,
            96485.6043956044,
            106932.1978021978,
            103878.79120879121,
            48602.307692307695,
            59787.36263736264,
            70972.41758241758,
            82157.47252747254,
            93342.52747252748,
            104527.58241758242,
            115712.63736263735,
            126897.69230769231,
            138082.74725274724,
            149267.8021978022,
            308952.85714285716
          ]
        }
      },
      {
        "id": "asset_3",
        "bua": 5500,
        "sellable": 5500,
        "land": 10666666.666666666,
        "cost": {
          "byLineId": {
            "land-cash": 1155555.5555555555,
            "site-prep": 50000,
            "infrastructure": 266666.6666666666,
            "structural": 0,
            "mep": 0,
            "finishing": 183333.3333333333,
            "marketing": 35555.55555555555,
            "legal": 17777.777777777774,
            "landscaping": 100000,
            "ffe": 45833.33333333333,
            "professional-fees": 51666.66666666667,
            "contingency": 32291.66666666667,
            "project-management": 19375
          },
          "byStage": {
            "land": 1155555.5555555555,
            "hard": 645833.3333333334,
            "soft": 156666.66666666666,
            "operating": 0
          },
          "total": 1958055.5555555553,
          "perPeriod": [
            1155555.5555555555,
            31720.085470085472,
            31492.165242165243,
            31264.245014245018,
            31036.32478632479,
            30808.40455840456,
            30580.484330484334,
            30352.564102564105,
            30124.643874643876,
            29896.72364672365,
            29668.80341880342,
            29779.50752950753,
            33003.76475376476,
            32061.35531135531,
            15000.712250712251,
            18452.889702889704,
            21905.067155067154,
            25357.244607244607,
            28809.42205942206,
            32261.59951159951,
            35713.77696377696,
            39165.95441595441,
            42618.131868131866,
            46070.309320309316,
            95355.82010582008
          ]
        }
      },
      {
        "id": "asset_4",
        "bua": 4400,
        "sellable": 4400,
        "land": 8533333.333333334,
        "cost": {
          "byLineId": {
            "land-cash": 739555.5555555556,
            "site-prep": 32000,
            "infrastructure": 170666.66666666666,
            "structural": 0,
            "mep": 0,
            "finishing": 117333.33333333333,
            "marketing": 22755.55555555556,
            "legal": 11377.77777777778,
            "landscaping": 64000,
            "ffe": 29333.333333333332,
            "professional-fees": 33066.666666666664,
            "contingency": 20666.666666666668,
            "project-management": 12399.999999999998
          },
          "byStage": {
            "land": 739555.5555555556,
            "hard": 413333.3333333333,
            "soft": 100266.66666666667,
            "operating": 0
          },
          "total": 1253155.5555555555,
          "perPeriod": [
            739555.5555555556,
            20300.854700854703,
            20154.985754985755,
            20009.11680911681,
            19863.247863247863,
            19717.37891737892,
            19571.50997150997,
            19425.641025641027,
            19279.77207977208,
            19133.903133903135,
            18988.034188034188,
            19058.88481888482,
            21122.40944240944,
            20519.2673992674,
            9600.45584045584,
            11809.849409849408,
            14019.24297924298,
            16228.636548636547,
            18438.030118030118,
            20647.42368742369,
            22856.81725681726,
            25066.210826210827,
            27275.604395604398,
            29484.997964997965,
            61027.72486772486
          ]
        }
      }
    ],
    "perPhase": [
      {
        "id": "phase_1",
        "cost": {
          "byAssetId": {
            "asset_1": {
              "byLineId": {
                "land-cash": 6656000,
                "site-prep": 288000,
                "infrastructure": 1536000,
                "structural": 0,
                "mep": 0,
                "finishing": 1056000,
                "marketing": 204800,
                "legal": 102400,
                "landscaping": 576000,
                "ffe": 264000,
                "professional-fees": 297600,
                "contingency": 186000,
                "project-management": 111600
              },
              "byStage": {
                "land": 6656000,
                "hard": 3720000,
                "soft": 902400,
                "operating": 0
              },
              "total": 11278400,
              "perPeriod": [
                6656000,
                182707.6923076923,
                181394.8717948718,
                180082.05128205128,
                178769.23076923078,
                177456.41025641025,
                176143.58974358975,
                174830.76923076922,
                173517.94871794872,
                172205.12820512822,
                170892.3076923077,
                171529.96336996337,
                190101.68498168496,
                184673.40659340663,
                86404.10256410256,
                106288.6446886447,
                126173.18681318681,
                146057.7289377289,
                165942.2710622711,
                185826.8131868132,
                205711.35531135532,
                225595.89743589744,
                245480.43956043955,
                265364.98168498167,
                549249.5238095238
              ]
            },
            "asset_2": {
              "byLineId": {
                "land-cash": 3744000,
                "site-prep": 162000,
                "infrastructure": 864000,
                "structural": 0,
                "mep": 0,
                "finishing": 594000,
                "marketing": 115200,
                "legal": 57600,
                "landscaping": 324000,
                "ffe": 148500,
                "professional-fees": 167400,
                "contingency": 104625,
                "project-management": 62775
              },
              "byStage": {
                "land": 3744000,
                "hard": 2092500,
                "soft": 507600,
                "operating": 0
              },
              "total": 6344100,
              "perPeriod": [
                3744000,
                102773.07692307694,
                102034.61538461539,
                101296.15384615386,
                100557.69230769231,
                99819.23076923078,
                99080.76923076923,
                98342.3076923077,
                97603.84615384616,
                96865.38461538462,
                96126.92307692308,
                96485.6043956044,
                106932.1978021978,
                103878.79120879121,
                48602.307692307695,
                59787.36263736264,
                70972.41758241758,
                82157.47252747254,
                93342.52747252748,
                104527.58241758242,
                115712.63736263735,
                126897.69230769231,
                138082.74725274724,
                149267.8021978022,
                308952.85714285716
              ]
            },
            "asset_3": {
              "byLineId": {
                "land-cash": 1155555.5555555555,
                "site-prep": 50000,
                "infrastructure": 266666.6666666666,
                "structural": 0,
                "mep": 0,
                "finishing": 183333.3333333333,
                "marketing": 35555.55555555555,
                "legal": 17777.777777777774,
                "landscaping": 100000,
                "ffe": 45833.33333333333,
                "professional-fees": 51666.66666666667,
                "contingency": 32291.66666666667,
                "project-management": 19375
              },
              "byStage": {
                "land": 1155555.5555555555,
                "hard": 645833.3333333334,
                "soft": 156666.66666666666,
                "operating": 0
              },
              "total": 1958055.5555555553,
              "perPeriod": [
                1155555.5555555555,
                31720.085470085472,
                31492.165242165243,
                31264.245014245018,
                31036.32478632479,
                30808.40455840456,
                30580.484330484334,
                30352.564102564105,
                30124.643874643876,
                29896.72364672365,
                29668.80341880342,
                29779.50752950753,
                33003.76475376476,
                32061.35531135531,
                15000.712250712251,
                18452.889702889704,
                21905.067155067154,
                25357.244607244607,
                28809.42205942206,
                32261.59951159951,
                35713.77696377696,
                39165.95441595441,
                42618.131868131866,
                46070.309320309316,
                95355.82010582008
              ]
            },
            "asset_4": {
              "byLineId": {
                "land-cash": 739555.5555555556,
                "site-prep": 32000,
                "infrastructure": 170666.66666666666,
                "structural": 0,
                "mep": 0,
                "finishing": 117333.33333333333,
                "marketing": 22755.55555555556,
                "legal": 11377.77777777778,
                "landscaping": 64000,
                "ffe": 29333.333333333332,
                "professional-fees": 33066.666666666664,
                "contingency": 20666.666666666668,
                "project-management": 12399.999999999998
              },
              "byStage": {
                "land": 739555.5555555556,
                "hard": 413333.3333333333,
                "soft": 100266.66666666667,
                "operating": 0
              },
              "total": 1253155.5555555555,
              "perPeriod": [
                739555.5555555556,
                20300.854700854703,
                20154.985754985755,
                20009.11680911681,
                19863.247863247863,
                19717.37891737892,
                19571.50997150997,
                19425.641025641027,
                19279.77207977208,
                19133.903133903135,
                18988.034188034188,
                19058.88481888482,
                21122.40944240944,
                20519.2673992674,
                9600.45584045584,
                11809.849409849408,
                14019.24297924298,
                16228.636548636547,
                18438.030118030118,
                20647.42368742369,
                22856.81725681726,
                25066.210826210827,
                27275.604395604398,
                29484.997964997965,
                61027.72486772486
              ]
            }
          },
          "byStage": {
            "land": 12295111.111111112,
            "hard": 6871666.666666666,
            "soft": 1666933.3333333335,
            "operating": 0
          },
          "total": 20833711.111111112,
          "perPeriod": [
            12295111.111111112,
            337501.70940170944,
            335076.6381766382,
            332651.56695156696,
            330226.4957264958,
            327801.4245014245,
            325376.35327635333,
            322951.28205128206,
            320526.21082621085,
            318101.1396011397,
            315676.0683760684,
            316853.96011396014,
            351160.056980057,
            341132.82051282056,
            159607.57834757832,
            196338.74643874643,
            233069.91452991456,
            269801.0826210826,
            306532.2507122507,
            343263.41880341887,
            379994.58689458686,
            416725.754985755,
            453456.92307692306,
            490188.0911680911,
            1014585.9259259258
          ]
        }
      },
      {
        "id": "phase_2",
        "cost": {
          "byAssetId": {},
          "byStage": {
            "land": 0,
            "hard": 0,
            "soft": 0,
            "operating": 0
          },
          "total": 0,
          "perPeriod": [
            0,
            0,
            0,
            0,
            0,
            0,
            0,
            0,
            0,
            0,
            0,
            0,
            0,
            0,
            0,
            0,
            0,
            0,
            0
          ]
        }
      }
    ],
    "perTranche": [
      {
        "id": "tranche_1",
        "fin": {
          "periods": 84,
          "periodicRate": 0.0062499999999999995,
          "drawSchedule": [
            520842.77777777775,
            520842.77777777775,
            520842.77777777775,
            520842.77777777775,
            520842.77777777775,
            520842.77777777775,
            520842.77777777775,
            520842.77777777775,
            520842.77777777775,
            520842.77777777775,
            520842.77777777775,
            520842.77777777775,
            520842.77777777775,
            520842.77777777775,
            520842.77777777775,
            520842.77777777775,
            520842.77777777775,
            520842.77777777775,
            520842.77777777775,
            520842.77777777775,
            520842.77777777775,
            520842.77777777775,
            520842.77777777775,
            520842.77777777775,
            0,
            0,
            0,
            0,
            0,
            0,
            0,
            0,
            0,
            0,
            0,
            0,
            0,
            0,
            0,
            0,
            0,
            0,
            0,
            0,
            0,
            0,
            0,
            0,
            0,
            0,
            0,
            0,
            0,
            0,
            0,
            0,
            0,
            0,
            0,
            0,
            0,
            0,
            0,
            0,
            0,
            0,
            0,
            0,
            0,
            0,
            0,
            0,
            0,
            0,
            0,
            0,
            0,
            0,
            0,
            0,
            0,
            0,
            0,
            0
          ],
          "outstandingBalance": [
            524098.0451388889,
            1051471.703059896,
            1582141.446342909,
            2116127.875521441,
            2653451.7198823392,
            3194133.838270493,
            3738195.2198985727,
            4285656.985161827,
            4836540.386457978,
            5390866.80901223,
            5948657.771707445,
            6509934.927919506,
            7074720.066357892,
            7643035.111911518,
            8214902.126499854,
            8790343.309929367,
            9369381.000755316,
            9952037.677148925,
            10538335.957769996,
            11128298.602644946,
            11721948.514050366,
            12319308.73740207,
            12920402.462149723,
            13525253.022677047,
            13316915.911565935,
            13108578.800454823,
            12900241.689343711,
            12691904.5782326,
            12483567.467121487,
            12275230.356010376,
            12066893.244899264,
            11858556.133788152,
            11650219.02267704,
            11441881.911565928,
            11233544.800454816,
            11025207.689343704,
            10816870.578232592,
            10608533.46712148,
            10400196.356010368,
            10191859.244899256,
            9983522.133788144,
            9775185.022677032,
            9566847.91156592,
            9358510.800454808,
            9150173.689343696,
            8941836.578232585,
            8733499.467121473,
            8525162.35601036,
            8316825.24489925,
            8108488.133788139,
            7900151.022677028,
            7691813.911565917,
            7483476.800454806,
            7275139.689343695,
            7066802.578232584,
            6858465.467121473,
            6650128.356010362,
            6441791.244899251,
            6233454.13378814,
            6025117.022677029,
            5816779.911565918,
            5608442.800454807,
            5400105.6893436955,
            5191768.5782325845,
            4983431.4671214735,
            4775094.3560103625,
            4566757.2448992515,
            4358420.1337881405,
            4150083.0226770295,
            3941745.9115659185,
            3733408.8004548075,
            3525071.6893436965,
            3316734.5782325855,
            3108397.4671214744,
            2900060.3560103634,
            2691723.2448992524,
            2483386.1337881414,
            2275049.0226770304,
            2066711.9115659192,
            1858374.800454808,
            1650037.6893436967,
            1441700.5782325855,
            1233363.4671214742,
            1025026.3560103631
          ],
          "interestAccrued": [
            3255.267361111111,
            6530.880143229166,
            9826.96550523546,
            13143.651400754292,
            16481.06658312012,
            19839.34061037573,
            23218.60385030169,
            26618.987485477188,
            30040.62351837253,
            33483.64477647347,
            36948.184917437546,
            40434.37843428264,
            43942.36066060802,
            47472.26777584793,
            51024.23681055809,
            54598.40565173519,
            58194.913048169656,
            61813.89861583183,
            65455.50284329189,
            69119.86709717358,
            72807.13362764202,
            76517.4455739259,
            80250.94696987404,
            84007.78274954687,
            84532.83139173154,
            83230.7244472871,
            81928.61750284264,
            80626.5105583982,
            79324.40361395373,
            78022.29666950929,
            76720.18972506485,
            75418.08278062039,
            74115.97583617595,
            72813.86889173149,
            71511.76194728704,
            70209.6550028426,
            68907.54805839814,
            67605.4411139537,
            66303.33416950924,
            65001.227225064795,
            63699.120280620344,
            62397.01333617589,
            61094.90639173145,
            59792.799447287,
            58490.69250284255,
            57188.585558398096,
            55886.47861395365,
            54584.3716695092,
            53282.26472506475,
            51980.157780620306,
            50678.05083617586,
            49375.94389173142,
            48073.836947286974,
            46771.73000284253,
            45469.62305839809,
            44167.51611395364,
            42865.4091695092,
            41563.302225064755,
            40261.19528062031,
            38959.08833617587,
            37656.981391731424,
            36354.87444728698,
            35052.76750284254,
            33750.66055839809,
            32448.55361395365,
            31146.446669509205,
            29844.339725064765,
            28542.23278062032,
            27240.125836175877,
            25938.018891731434,
            24635.91194728699,
            23333.805002842546,
            22031.698058398102,
            20729.59111395366,
            19427.484169509215,
            18125.37722506477,
            16823.270280620327,
            15521.163336175883,
            14219.05639173144,
            12916.949447286994,
            11614.842502842548,
            10312.735558398104,
            9010.628613953659,
            7708.521669509213
          ],
          "interestCapitalized": [
            3255.267361111111,
            6530.880143229166,
            9826.96550523546,
            13143.651400754292,
            16481.06658312012,
            19839.34061037573,
            23218.60385030169,
            26618.987485477188,
            30040.62351837253,
            33483.64477647347,
            36948.184917437546,
            40434.37843428264,
            43942.36066060802,
            47472.26777584793,
            51024.23681055809,
            54598.40565173519,
            58194.913048169656,
            61813.89861583183,
            65455.50284329189,
            69119.86709717358,
            72807.13362764202,
            76517.4455739259,
            80250.94696987404,
            84007.78274954687,
            0,
            0,
            0,
            0,
            0,
            0,
            0,
            0,
            0,
            0,
            0,
            0,
            0,
            0,
            0,
            0,
            0,
            0,
            0,
            0,
            0,
            0,
            0,
            0,
            0,
            0,
            0,
            0,
            0,
            0,
            0,
            0,
            0,
            0,
            0,
            0,
            0,
            0,
            0,
            0,
            0,
            0,
            0,
            0,
            0,
            0,
            0,
            0,
            0,
            0,
            0,
            0,
            0,
            0,
            0,
            0,
            0,
            0,
            0,
            0
          ],
          "interestPaid": [
            0,
            0,
            0,
            0,
            0,
            0,
            0,
            0,
            0,
            0,
            0,
            0,
            0,
            0,
            0,
            0,
            0,
            0,
            0,
            0,
            0,
            0,
            0,
            0,
            84532.83139173154,
            83230.7244472871,
            81928.61750284264,
            80626.5105583982,
            79324.40361395373,
            78022.29666950929,
            76720.18972506485,
            75418.08278062039,
            74115.97583617595,
            72813.86889173149,
            71511.76194728704,
            70209.6550028426,
            68907.54805839814,
            67605.4411139537,
            66303.33416950924,
            65001.227225064795,
            63699.120280620344,
            62397.01333617589,
            61094.90639173145,
            59792.799447287,
            58490.69250284255,
            57188.585558398096,
            55886.47861395365,
            54584.3716695092,
            53282.26472506475,
            51980.157780620306,
            50678.05083617586,
            49375.94389173142,
            48073.836947286974,
            46771.73000284253,
            45469.62305839809,
            44167.51611395364,
            42865.4091695092,
            41563.302225064755,
            40261.19528062031,
            38959.08833617587,
            37656.981391731424,
            36354.87444728698,
            35052.76750284254,
            33750.66055839809,
            32448.55361395365,
            31146.446669509205,
            29844.339725064765,
            28542.23278062032,
            27240.125836175877,
            25938.018891731434,
            24635.91194728699,
            23333.805002842546,
            22031.698058398102,
            20729.59111395366,
            19427.484169509215,
            18125.37722506477,
            16823.270280620327,
            15521.163336175883,
            14219.05639173144,
            12916.949447286994,
            11614.842502842548,
            10312.735558398104,
            9010.628613953659,
            7708.521669509213
          ],
          "principalRepaid": [
            0,
            0,
            0,
            0,
            0,
            0,
            0,
            0,
            0,
            0,
            0,
            0,
            0,
            0,
            0,
            0,
            0,
            0,
            0,
            0,
            0,
            0,
            0,
            0,
            208337.11111111115,
            208337.11111111115,
            208337.11111111115,
            208337.11111111115,
            208337.11111111115,
            208337.11111111115,
            208337.11111111115,
            208337.11111111115,
            208337.11111111115,
            208337.11111111115,
            208337.11111111115,
            208337.11111111115,
            208337.11111111115,
            208337.11111111115,
            208337.11111111115,
            208337.11111111115,
            208337.11111111115,
            208337.11111111115,
            208337.11111111115,
            208337.11111111115,
            208337.11111111115,
            208337.11111111115,
            208337.11111111115,
            208337.11111111115,
            208337.11111111115,
            208337.11111111115,
            208337.11111111115,
            208337.11111111115,
            208337.11111111115,
            208337.11111111115,
            208337.11111111115,
            208337.11111111115,
            208337.11111111115,
            208337.11111111115,
            208337.11111111115,
            208337.11111111115,
            208337.11111111115,
            208337.11111111115,
            208337.11111111115,
            208337.11111111115,
            208337.11111111115,
            208337.11111111115,
            208337.11111111115,
            208337.11111111115,
            208337.11111111115,
            208337.11111111115,
            208337.11111111115,
            208337.11111111115,
            208337.11111111115,
            208337.11111111115,
            208337.11111111115,
            208337.11111111115,
            208337.11111111115,
            208337.11111111115,
            208337.11111111115,
            208337.11111111115,
            208337.11111111115,
            208337.11111111115,
            208337.11111111115,
            208337.11111111115
          ],
          "totalDebt": 12500226.66666667,
          "totalInterest": 3792266.9478475964,
          "totalRepayment": 12500226.666666681
        }
      },
      {
        "id": "tranche_2",
        "fin": {
          "periods": 72,
          "periodicRate": 0.0062499999999999995,
          "drawSchedule": [
            0,
            0,
            0,
            0,
            0,
            0,
            0,
            0,
            0,
            0,
            0,
            0,
            0,
            0,
            0,
            0,
            0,
            0,
            0,
            0,
            0,
            0,
            0,
            0,
            0,
            0,
            0,
            0,
            0,
            0,
            0,
            0,
            0,
            0,
            0,
            0,
            0,
            0,
            0,
            0,
            0,
            0,
            0,
            0,
            0,
            0,
            0,
            0,
            0,
            0,
            0,
            0,
            0,
            0,
            0,
            0,
            0,
            0,
            0,
            0,
            0,
            0,
            0,
            0,
            0,
            0,
            0,
            0,
            0,
            0,
            0,
            0
          ],
          "outstandingBalance": [
            0,
            0,
            0,
            0,
            0,
            0,
            0,
            0,
            0,
            0,
            0,
            0,
            0,
            0,
            0,
            0,
            0,
            0,
            0,
            0,
            0,
            0,
            0,
            0,
            0,
            0,
            0,
            0,
            0,
            0,
            0,
            0,
            0,
            0,
            0,
            0,
            0,
            0,
            0,
            0,
            0,
            0,
            0,
            0,
            0,
            0,
            0,
            0,
            0,
            0,
            0,
            0,
            0,
            0,
            0,
            0,
            0,
            0,
            0,
            0,
            0,
            0,
            0,
            0,
            0,
            0,
            0,
            0,
            0,
            0,
            0,
            0
          ],
          "interestAccrued": [
            0,
            0,
            0,
            0,
            0,
            0,
            0,
            0,
            0,
            0,
            0,
            0,
            0,
            0,
            0,
            0,
            0,
            0,
            0,
            0,
            0,
            0,
            0,
            0,
            0,
            0,
            0,
            0,
            0,
            0,
            0,
            0,
            0,
            0,
            0,
            0,
            0,
            0,
            0,
            0,
            0,
            0,
            0,
            0,
            0,
            0,
            0,
            0,
            0,
            0,
            0,
            0,
            0,
            0,
            0,
            0,
            0,
            0,
            0,
            0,
            0,
            0,
            0,
            0,
            0,
            0,
            0,
            0,
            0,
            0,
            0,
            0
          ],
          "interestCapitalized": [
            0,
            0,
            0,
            0,
            0,
            0,
            0,
            0,
            0,
            0,
            0,
            0,
            0,
            0,
            0,
            0,
            0,
            0,
            0,
            0,
            0,
            0,
            0,
            0,
            0,
            0,
            0,
            0,
            0,
            0,
            0,
            0,
            0,
            0,
            0,
            0,
            0,
            0,
            0,
            0,
            0,
            0,
            0,
            0,
            0,
            0,
            0,
            0,
            0,
            0,
            0,
            0,
            0,
            0,
            0,
            0,
            0,
            0,
            0,
            0,
            0,
            0,
            0,
            0,
            0,
            0,
            0,
            0,
            0,
            0,
            0,
            0
          ],
          "interestPaid": [
            0,
            0,
            0,
            0,
            0,
            0,
            0,
            0,
            0,
            0,
            0,
            0,
            0,
            0,
            0,
            0,
            0,
            0,
            0,
            0,
            0,
            0,
            0,
            0,
            0,
            0,
            0,
            0,
            0,
            0,
            0,
            0,
            0,
            0,
            0,
            0,
            0,
            0,
            0,
            0,
            0,
            0,
            0,
            0,
            0,
            0,
            0,
            0,
            0,
            0,
            0,
            0,
            0,
            0,
            0,
            0,
            0,
            0,
            0,
            0,
            0,
            0,
            0,
            0,
            0,
            0,
            0,
            0,
            0,
            0,
            0,
            0
          ],
          "principalRepaid": [
            0,
            0,
            0,
            0,
            0,
            0,
            0,
            0,
            0,
            0,
            0,
            0,
            0,
            0,
            0,
            0,
            0,
            0,
            0,
            0,
            0,
            0,
            0,
            0,
            0,
            0,
            0,
            0,
            0,
            0,
            0,
            0,
            0,
            0,
            0,
            0,
            0,
            0,
            0,
            0,
            0,
            0,
            0,
            0,
            0,
            0,
            0,
            0,
            0,
            0,
            0,
            0,
            0,
            0,
            0,
            0,
            0,
            0,
            0,
            0,
            0,
            0,
            0,
            0,
            0,
            0,
            0,
            0,
            0,
            0,
            0,
            0
          ],
          "totalDebt": 0,
          "totalInterest": 0,
          "totalRepayment": 0
        }
      }
    ],
    "distSamples": {
      "even": [
        0.08333333333333333,
        0.08333333333333333,
        0.08333333333333333,
        0.08333333333333333,
        0.08333333333333333,
        0.08333333333333333,
        0.08333333333333333,
        0.08333333333333333,
        0.08333333333333333,
        0.08333333333333333,
        0.08333333333333333,
        0.08333333333333333
      ],
      "frontloaded": [
        0.15384615384615385,
        0.14102564102564102,
        0.1282051282051282,
        0.11538461538461539,
        0.10256410256410256,
        0.08974358974358974,
        0.07692307692307693,
        0.0641025641025641,
        0.05128205128205128,
        0.038461538461538464,
        0.02564102564102564,
        0.01282051282051282
      ],
      "backloaded": [
        0.01282051282051282,
        0.02564102564102564,
        0.038461538461538464,
        0.05128205128205128,
        0.0641025641025641,
        0.07692307692307693,
        0.08974358974358974,
        0.10256410256410256,
        0.11538461538461539,
        0.1282051282051282,
        0.14102564102564102,
        0.15384615384615385
      ],
      "manual": [
        0.5,
        0.16666666666666666,
        0.16666666666666666,
        0.16666666666666666
      ]
    }
  }
}